{
    "items": [
        {
            "title": "Annicken+Morten=sant",
            "url": "https://tv.nrk.no/program/DKTT60003016",
            "description": "",
            "Tilgjengelig fra": "28. mai 2016 kl. 10",
            "Tilgjengelig til": "Alltid tilgjengelig",
            "Tilgjengelig i": "Verden",
            "Aldersgrense": "",
            "Produksjonsår": "",
            "Lengde": "3 timer og 20 minutter",
            "Første gang sendt": "NRK1 · Lørdag 28. mai 2016 kl. 11",
            "Siste gang sendt": "NRK3 · Søndag 29. mai 2016 kl. 23",
            "src": "https://gfx.nrk.no/RVi9G1-7z6DNPH6f7MVrqQQvhc3EuG1adxMV6L3Kqlfw"
        },
        {
            "title": "XYZ",
            "url": "https://tv.nrk.no/serie/xyz",
            "description": "Blindt møte med Petter Nome.",
            "Tilgjengelig fra": "11. oktober 2022 kl. 00",
            "Tilgjengelig til": "Alltid tilgjengelig",
            "Tilgjengelig i": "Verden",
            "Aldersgrense": "6+",
            "Produksjonsår": "1997",
            "Lengde": "30 minutter",
            "Første gang sendt": "NRK1 · Fredag 28. november 1997 kl. 23",
            "Siste gang sendt": "NRK1 · Fredag 28. november 1997 kl. 23",
            "src": "https://gfx.nrk.no/33VnbBE6Ugc36Og4Inb7-AevC-B2sNW3A1BLPyYRqUAg"
        }
    ]
}